design/app/max10_galvano/source/pos_pid.v
module pos_pid
(
    input  wire        sys_rstn,
    input  wire        clk_pid,
        
    input  wire [15:0] kp,
    input  wire [15:0] ki,
    input  wire [15:0] kd,
    
    input  wire [15:0] dac_limit,
    input  wire [23:0] pid_i_saturation,
    input  wire        spi_new_target_valid,
    input  wire [15:0] pos_target,
    input  wire        pos_adc_data_valid,
    input  wire [15:0] pos_adc,
    output reg  [15:0] pos_dac
);

reg signed [47:0] P, I, D, error, error_last, integrator;
reg signed [47:0] pid;
wire [15:0] limit0;
wire [15:0] limit1;

assign limit0 = 32768 - dac_limit;
assign limit1 = 32768 + dac_limit;

reg [1:0] spi_new_target_valid_dly;
reg [1:0] pos_adc_data_valid_dly;

// bpann
reg signed [ 7:0] w000, w001, w002, w010, w011, w012, w020, w021, w022, w100, w101, w102, w110, w111, w112, w120, w121, w122;
reg signed [15:0] b10, b11, b12, b20, b21, b22;
reg signed [15:0] e10, e11, e12, e20, e21, e22;
reg signed [15:0] x00, x01, x02, x10, x11, x12, x20, x21, x22;

reg         [7:0] bpann_loop;

localparam STATE0 = 0;
localparam STATE1 = 1;
localparam STATE2 = 2;
localparam STATE3 = 3;
localparam STATE4 = 4;
localparam STATE5 = 5;
localparam STATE6 = 6;
localparam STATE7 = 7;
localparam STATE8 = 8;
localparam STATE9 = 9;
localparam STATE10= 10;
localparam STATE11= 11;
localparam STATE12= 12;
localparam STATE13= 12;
reg [3:0] state;
always @(negedge sys_rstn or posedge clk_pid) begin
    if (!sys_rstn) begin
        state <= STATE0;
        error <= 0;
        error_last <= 0;
        integrator <= 0;
        pid <= 0;
        pos_dac <= 32768;
        
        bpann_loop <= 0;
        w000 <= 64; 
        w001 <= 64; 
        w002 <= 64; 
        w010 <= 64; 
        w011 <= 64; 
        w012 <= 64; 
        w020 <= 64; 
        w021 <= 64; 
        w022 <= 64;       
        w100 <= 64; 
        w101 <= 64; 
        w102 <= 64; 
        w110 <= 64; 
        w111 <= 64; 
        w112 <= 64; 
        w120 <= 64; 
        w121 <= 64; 
        w122 <= 64;      

        b10  <= 16384; 
        b11  <= 16384; 
        b12  <= 16384;
        b20  <= 16384; 
        b21  <= 16384; 
        b22  <= 16384;
    end
    else if (clk_pid) begin
        spi_new_target_valid_dly <= {spi_new_target_valid_dly[0], spi_new_target_valid};
        pos_adc_data_valid_dly   <= {pos_adc_data_valid_dly[0],   pos_adc_data_valid};
        case(state)
            STATE0: begin
                if (spi_new_target_valid_dly == 2'b01) begin
                    bpann_loop <= 0;
                    state <= STATE1;
                end
            end
            STATE1: begin
                if (pos_adc_data_valid_dly == 2'b01) begin
                    error <= 0;
                    error_last <= 0;
                    integrator <= 0;
                    state <= STATE2;
                end
            end
            STATE2: begin
                if (pos_adc_data_valid_dly == 2'b01) begin
                    error <= $signed({1'b0, pos_target}) - $signed({1'b0, pos_adc});
                    error_last <= error;
                    state <= STATE3;
                end
            end
            STATE3: begin
                P <= ($signed({1'b0, kp}) * error) >>> 10;
                I <= ($signed({1'b0, ki}) * integrator) >>> 10;
                D <= ($signed({1'b0, kd}) * (error - error_last)) >>> 8;
                integrator <= integrator + error;
                state <= STATE4;
            end
            STATE4: begin
                pid <= (P + I + D);
                if ((-integrator > $signed({1'b0, pid_i_saturation})) || (integrator > $signed({1'b0, pid_i_saturation})))
                    integrator <= $signed({1'b0, pid_i_saturation});
                state <= STATE5;
            end
            STATE5: begin
                if (pid > $signed({1'b0, dac_limit})) begin
                    x00 <=  32767;
                end
                else if (-pid > $signed({1'b0, dac_limit})) begin
                    x00 <= -32767;
                end
                else begin
                    x00 <= pid  * 32768 / dac_limit;
                end
                x01 <= (pos_adc) / 2;
                x02 <= (error_last - error) / 2;
                state <= STATE6;
            end
            STATE6: begin
                bpann_loop <= bpann_loop + 1;
                task_bpnn_f((w000*x00 + w010*x01 + w020*x02)/128 + b10, x10);
                task_bpnn_f((w001*x00 + w011*x01 + w021*x02)/128 + b11, x11);
                task_bpnn_f((w002*x00 + w012*x01 + w022*x02)/128 + b12, x12);
                state <= STATE7;
            end
            STATE7: begin
                task_bpnn_f((w100*x10 + w110*x11 + w120*x12)/128 + b20, x20);
                task_bpnn_f((w101*x10 + w111*x11 + w121*x12)/128 + b21, x21);
                task_bpnn_f((w102*x10 + w112*x11 + w122*x12)/128 + b22, x22);
                state <= STATE8;
            end
            STATE8: begin
                pos_dac <= 32768 + ((x20*dac_limit)/32768);
                if (bpann_loop > 10) begin
                    state <= STATE9;
                    pos_dac <= 32768;
                    e20 <= (x20) * (32767 - x20) * (16384 - x20) / 1073741824;          // F, Oj * (1 - Oj) * (0.5 - Oj)
                    e21 <= (x21) * (32767 - x21) * (pos_target/2   - x21) / 1073741824; // P, Oj * (1 - Oj) * (T   - Oj)
                    e22 <= (x22) * (32767 - x22) * (0     - x22) / 1073741824;          // V, Oj * (1 - Oj) * (0   - Oj)
                end
                else begin
                    state <= STATE2;
                end
            end
            STATE9: begin
                e10 <= x10 * (32767 - x10) * (w100*e20 + w101*e21 + w102*e22) / 137438953472; // Oj * (1 - Oj) * Sigma(Errk * wjk)
                e11 <= x11 * (32767 - x11) * (w110*e20 + w111*e21 + w112*e22) / 137438953472; // Oj * (1 - Oj) * Sigma(Errk * wjk)
                e12 <= x12 * (32767 - x12) * (w120*e20 + w121*e21 + w122*e22) / 137438953472; // Oj * (1 - Oj) * Sigma(Errk * wjk)
                state <= STATE10;
            end
            STATE10: begin
                w000 <= w000 + ((x00*e10)/8388608); 
                w001 <= w001 + ((x00*e11)/8388608); 
                w002 <= w002 + ((x00*e12)/8388608);
                w010 <= w010 + ((x01*e10)/8388608); 
                w011 <= w011 + ((x01*e11)/8388608); 
                w012 <= w012 + ((x01*e12)/8388608);
                w020 <= w020 + ((x02*e10)/8388608); 
                w021 <= w021 + ((x02*e11)/8388608); 
                w022 <= w022 + ((x02*e12)/8388608);
                w100 <= w100 + ((x10*e20)/8388608); 
                w101 <= w101 + ((x10*e21)/8388608); 
                w102 <= w102 + ((x10*e22)/8388608);
                w110 <= w110 + ((x11*e20)/8388608); 
                w111 <= w111 + ((x11*e21)/8388608); 
                w112 <= w112 + ((x11*e22)/8388608);
                w120 <= w120 + ((x12*e20)/8388608); 
                w121 <= w121 + ((x12*e22)/8388608); 
                w122 <= w122 + ((x12*e22)/8388608);
                
                b10 <= b10 + e10; 
                b11 <= b11 + e11; 
                b12 <= b12 + e12;
                b20 <= b20 + e20; 
                b21 <= b21 + e21; 
                b22 <= b22 + e22;
                
                state <= STATE0;
            end
        endcase
    end
end

task task_bpnn_f;
    input  reg signed [15:0] x;
    output reg signed [15:0] y;
    y = 16384 + (16384 * x / (1 + (x > 0) ? x : (-x)));
endtask

endmodule

design/app/max10_galvano/source/pos_pid_tb.v
module tb();
    reg  clk, reset, spi_new_target_valid, pos_adc_data_valid;
    reg  [15:0] pos_adc, pos_target;
    wire [15:0] pos_dac;
    
    pos_pid pid
    (
       .sys_rstn(reset),
       .clk_pid(clk),
       
       .kp(16'd1200),
       .ki(16'd60),
       .kd(16'd48000),
       
       .dac_limit(16'd5000),
       .pid_i_saturation(24'd5000),
       .spi_new_target_valid(spi_new_target_valid),
       .pos_target(pos_target),
       .pos_adc_data_valid(pos_adc_data_valid),
       .pos_adc(pos_adc),
       .pos_dac(pos_dac)
    );

    always #5    clk = ~clk;
    always #40   pos_adc_data_valid   = ~pos_adc_data_valid;
    always #2000 spi_new_target_valid = ~spi_new_target_valid;

    always @(posedge pos_adc_data_valid)
        pos_adc = pos_adc + 200;

    initial begin
        clk = 0;
        reset = 0;
        pos_adc = 0;
        pos_adc_data_valid = 0;
        spi_new_target_valid = 0;
        pos_target = 1000;
        $dumpfile("test.vcd");
        $dumpvars;
        
        $dumpvars(0, tb.pid.w[0][0][0]);
        $dumpvars(0, tb.pid.w[0][0][1]);
        $dumpvars(0, tb.pid.w[0][0][2]);
        
        $dumpvars(0, tb.pid.w[1][0][0]);
        $dumpvars(0, tb.pid.w[1][0][1]);
        $dumpvars(0, tb.pid.w[1][0][2]);
        $dumpvars(0, tb.pid.w[1][1][0]);
        $dumpvars(0, tb.pid.w[1][1][1]);
        $dumpvars(0, tb.pid.w[1][1][2]);
        $dumpvars(0, tb.pid.w[1][2][0]);
        $dumpvars(0, tb.pid.w[1][2][1]);
        $dumpvars(0, tb.pid.w[1][2][2]);
        
        $dumpvars(0, tb.pid.x[0][0]);
        $dumpvars(0, tb.pid.x[0][1]);
        $dumpvars(0, tb.pid.x[0][2]);
        $dumpvars(0, tb.pid.x[1][0]);
        $dumpvars(0, tb.pid.x[1][1]);
        $dumpvars(0, tb.pid.x[1][2]);
        $dumpvars(0, tb.pid.x[2][0]);
        $dumpvars(0, tb.pid.x[2][1]);
        $dumpvars(0, tb.pid.x[2][2]);
        
        $dumpvars(0, tb.pid.e[1][0]);
        $dumpvars(0, tb.pid.e[1][1]);
        $dumpvars(0, tb.pid.e[1][2]);
        $dumpvars(0, tb.pid.e[2][0]);
        $dumpvars(0, tb.pid.e[2][1]);
        $dumpvars(0, tb.pid.e[2][2]);

        //$monitor($time,"dac: %d", pos_dac);
        #100 reset = 1;
        #50000 $finish;
    end
endmodule

design/app/max10_galvano/source/pid.vcd
$date
	Fri Dec 18 13:14:15 2020
$end
$version
	Icarus Verilog
$end
$timescale
	1s
$end
$scope module tb $end
$var wire 16 ! pos_dac [15:0] $end
$var reg 1 " clk $end
$var reg 16 # pos_adc [15:0] $end
$var reg 1 $ pos_adc_data_valid $end
$var reg 16 % pos_target [15:0] $end
$var reg 1 & reset $end
$var reg 1 ' spi_new_target_valid $end
$scope module pid $end
$var wire 1 " clk_pid $end
$var wire 16 ( dac_limit [15:0] $end
$var wire 16 ) kd [15:0] $end
$var wire 16 * ki [15:0] $end
$var wire 16 + kp [15:0] $end
$var wire 24 , pid_i_saturation [23:0] $end
$var wire 16 - pos_adc [15:0] $end
$var wire 1 $ pos_adc_data_valid $end
$var wire 16 . pos_target [15:0] $end
$var wire 1 ' spi_new_target_valid $end
$var wire 1 & sys_rstn $end
$var wire 16 / limit1 [15:0] $end
$var wire 16 0 limit0 [15:0] $end
$var reg 48 1 D [47:0] $end
$var reg 48 2 I [47:0] $end
$var reg 48 3 P [47:0] $end
$var reg 16 4 b10 [15:0] $end
$var reg 16 5 b11 [15:0] $end
$var reg 16 6 b12 [15:0] $end
$var reg 16 7 b20 [15:0] $end
$var reg 16 8 b21 [15:0] $end
$var reg 16 9 b22 [15:0] $end
$var reg 8 : bpann_loop [7:0] $end
$var reg 16 ; e10 [15:0] $end
$var reg 16 < e11 [15:0] $end
$var reg 16 = e12 [15:0] $end
$var reg 16 > e20 [15:0] $end
$var reg 16 ? e21 [15:0] $end
$var reg 16 @ e22 [15:0] $end
$var reg 48 A error [47:0] $end
$var reg 48 B error_last [47:0] $end
$var reg 48 C integrator [47:0] $end
$var reg 48 D pid [47:0] $end
$var reg 2 E pos_adc_data_valid_dly [1:0] $end
$var reg 16 F pos_dac [15:0] $end
$var reg 2 G spi_new_target_valid_dly [1:0] $end
$var reg 4 H state [3:0] $end
$var reg 8 I w000 [7:0] $end
$var reg 8 J w001 [7:0] $end
$var reg 8 K w002 [7:0] $end
$var reg 8 L w010 [7:0] $end
$var reg 8 M w011 [7:0] $end
$var reg 8 N w012 [7:0] $end
$var reg 8 O w020 [7:0] $end
$var reg 8 P w021 [7:0] $end
$var reg 8 Q w022 [7:0] $end
$var reg 8 R w100 [7:0] $end
$var reg 8 S w101 [7:0] $end
$var reg 8 T w102 [7:0] $end
$var reg 8 U w110 [7:0] $end
$var reg 8 V w111 [7:0] $end
$var reg 8 W w112 [7:0] $end
$var reg 8 X w120 [7:0] $end
$var reg 8 Y w121 [7:0] $end
$var reg 8 Z w122 [7:0] $end
$var reg 16 [ x00 [15:0] $end
$var reg 16 \ x01 [15:0] $end
$var reg 16 ] x02 [15:0] $end
$var reg 16 ^ x10 [15:0] $end
$var reg 16 _ x11 [15:0] $end
$var reg 16 ` x12 [15:0] $end
$var reg 16 a x20 [15:0] $end
$var reg 16 b x21 [15:0] $end
$var reg 16 c x22 [15:0] $end
$scope task task_bpnn_f $end
$var reg 16 d x [15:0] $end
$var reg 16 e y [15:0] $end
$upscope $end
$upscope $end
$upscope $end
$enddefinitions $end
#0
$dumpvars
bx e
bx d
bx c
bx b
bx a
bx `
bx _
bx ^
bx ]
bx \
bx [
b1000000 Z
b1000000 Y
b1000000 X
b1000000 W
b1000000 V
b1000000 U
b1000000 T
b1000000 S
b1000000 R
b1000000 Q
b1000000 P
b1000000 O
b1000000 N
b1000000 M
b1000000 L
b1000000 K
b1000000 J
b1000000 I
b0 H
bx G
b1000000000000000 F
bx E
b0 D
b0 C
b0 B
b0 A
bx @
bx ?
bx >
bx =
bx <
bx ;
b0 :
b100000000000000 9
b100000000000000 8
b100000000000000 7
b100000000000000 6
b100000000000000 5
b100000000000000 4
bx 3
bx 2
bx 1
b110110001111000 0
b1001001110001000 /
b1111101000 .
b0 -
b1001110001000 ,
b10010110000 +
b111100 *
b1011101110000000 )
b1001110001000 (
0'
0&
b1111101000 %
0$
b0 #
0"
b1000000000000000 !
$end
#5
1"
#10
0"
#15
1"
#20
0"
#25
1"
#30
0"
#35
1"
#40
b11110 #
b11110 -
0"
1$
#45
1"
#50
0"
#55
1"
#60
0"
#65
1"
#70
0"
#75
1"
#80
0"
0$
#85
1"
#90
0"
#95
1"
#100
0"
1&
#105
bx0 E
bx0 G
1"
#110
0"
#115
b0 E
b0 G
1"
#120
b111100 #
b111100 -
0"
1$
#125
b1 E
1"
#130
0"
#135
b11 E
1"
#140
0"
#145
1"
#150
0"
#155
1"
#160
0"
0$
#165
b10 E
1"
#170
0"
#175
b0 E
1"
#180
0"
#185
1"
#190
0"
#195
1"
#200
b1011010 #
b1011010 -
0"
1$
#205
b1 E
1"
#210
0"
#215
b11 E
1"
#220
0"
#225
1"
#230
0"
#235
1"
#240
0"
0$
#245
b10 E
1"
#250
0"
#255
b0 E
1"
#260
0"
#265
1"
#270
0"
#275
1"
#280
b1111000 #
b1111000 -
0"
1$
#285
b1 E
1"
#290
0"
#295
b11 E
1"
#300
0"
#305
1"
#310
0"
#315
1"
#320
0"
0$
#325
b10 E
1"
#330
0"
#335
b0 E
1"
#340
0"
#345
1"
#350
0"
#355
1"
#360
b10010110 #
b10010110 -
0"
1$
#365
b1 E
1"
#370
0"
#375
b11 E
1"
#380
0"
#385
1"
#390
0"
#395
1"
#400
0"
0$
#405
b10 E
1"
#410
0"
#415
b0 E
1"
#420
0"
#425
1"
#430
0"
#435
1"
#440
b10110100 #
b10110100 -
0"
1$
#445
b1 E
1"
#450
0"
#455
b11 E
1"
#460
0"
#465
1"
#470
0"
#475
1"
#480
0"
0$
#485
b10 E
1"
#490
0"
#495
b0 E
1"
#500
0"
#505
1"
#510
0"
#515
1"
#520
b11010010 #
b11010010 -
0"
1$
#525
b1 E
1"
#530
0"
#535
b11 E
1"
#540
0"
#545
1"
#550
0"
#555
1"
#560
0"
0$
#565
b10 E
1"
#570
0"
#575
b0 E
1"
#580
0"
#585
1"
#590
0"
#595
1"
#600
b11110000 #
b11110000 -
0"
1$
#605
b1 E
1"
#610
0"
#615
b11 E
1"
#620
0"
#625
1"
#630
0"
#635
1"
#640
0"
0$
#645
b10 E
1"
#650
0"
#655
b0 E
1"
#660
0"
#665
1"
#670
0"
#675
1"
#680
b100001110 #
b100001110 -
0"
1$
#685
b1 E
1"
#690
0"
#695
b11 E
1"
#700
0"
#705
1"
#710
0"
#715
1"
#720
0"
0$
#725
b10 E
1"
#730
0"
#735
b0 E
1"
#740
0"
#745
1"
#750
0"
#755
1"
#760
b100101100 #
b100101100 -
0"
1$
#765
b1 E
1"
#770
0"
#775
b11 E
1"
#780
0"
#785
1"
#790
0"
#795
1"
#800
0"
0$
#805
b10 E
1"
#810
0"
#815
b0 E
1"
#820
0"
#825
1"
#830
0"
#835
1"
#840
b101001010 #
b101001010 -
0"
1$
#845
b1 E
1"
#850
0"
#855
b11 E
1"
#860
0"
#865
1"
#870
0"
#875
1"
#880
0"
0$
#885
b10 E
1"
#890
0"
#895
b0 E
1"
#900
0"
#905
1"
#910
0"
#915
1"
#920
b101101000 #
b101101000 -
0"
1$
#925
b1 E
1"
#930
0"
#935
b11 E
1"
#940
0"
#945
1"
#950
0"
#955
1"
#960
0"
0$
#965
b10 E
1"
#970
0"
#975
b0 E
1"
#980
0"
#985
1"
#990
0"
#995
1"
#1000
b110000110 #
b110000110 -
0"
1$
#1005
b1 E
1"
#1010
0"
#1015
b11 E
1"
#1020
0"
#1025
1"
#1030
0"
#1035
1"
#1040
0"
0$
#1045
b10 E
1"
#1050
0"
#1055
b0 E
1"
#1060
0"
#1065
1"
#1070
0"
#1075
1"
#1080
b110100100 #
b110100100 -
0"
1$
#1085
b1 E
1"
#1090
0"
#1095
b11 E
1"
#1100
0"
#1105
1"
#1110
0"
#1115
1"
#1120
0"
0$
#1125
b10 E
1"
#1130
0"
#1135
b0 E
1"
#1140
0"
#1145
1"
#1150
0"
#1155
1"
#1160
b111000010 #
b111000010 -
0"
1$
#1165
b1 E
1"
#1170
0"
#1175
b11 E
1"
#1180
0"
#1185
1"
#1190
0"
#1195
1"
#1200
0"
0$
#1205
b10 E
1"
#1210
0"
#1215
b0 E
1"
#1220
0"
#1225
1"
#1230
0"
#1235
1"
#1240
b111100000 #
b111100000 -
0"
1$
#1245
b1 E
1"
#1250
0"
#1255
b11 E
1"
#1260
0"
#1265
1"
#1270
0"
#1275
1"
#1280
0"
0$
#1285
b10 E
1"
#1290
0"
#1295
b0 E
1"
#1300
0"
#1305
1"
#1310
0"
#1315
1"
#1320
b111111110 #
b111111110 -
0"
1$
#1325
b1 E
1"
#1330
0"
#1335
b11 E
1"
#1340
0"
#1345
1"
#1350
0"
#1355
1"
#1360
0"
0$
#1365
b10 E
1"
#1370
0"
#1375
b0 E
1"
#1380
0"
#1385
1"
#1390
0"
#1395
1"
#1400
b1000011100 #
b1000011100 -
0"
1$
#1405
b1 E
1"
#1410
0"
#1415
b11 E
1"
#1420
0"
#1425
1"
#1430
0"
#1435
1"
#1440
0"
0$
#1445
b10 E
1"
#1450
0"
#1455
b0 E
1"
#1460
0"
#1465
1"
#1470
0"
#1475
1"
#1480
b1000111010 #
b1000111010 -
0"
1$
#1485
b1 E
1"
#1490
0"
#1495
b11 E
1"
#1500
0"
#1505
1"
#1510
0"
#1515
1"
#1520
0"
0$
#1525
b10 E
1"
#1530
0"
#1535
b0 E
1"
#1540
0"
#1545
1"
#1550
0"
#1555
1"
#1560
b1001011000 #
b1001011000 -
0"
1$
#1565
b1 E
1"
#1570
0"
#1575
b11 E
1"
#1580
0"
#1585
1"
#1590
0"
#1595
1"
#1600
0"
0$
#1605
b10 E
1"
#1610
0"
#1615
b0 E
1"
#1620
0"
#1625
1"
#1630
0"
#1635
1"
#1640
b1001110110 #
b1001110110 -
0"
1$
#1645
b1 E
1"
#1650
0"
#1655
b11 E
1"
#1660
0"
#1665
1"
#1670
0"
#1675
1"
#1680
0"
0$
#1685
b10 E
1"
#1690
0"
#1695
b0 E
1"
#1700
0"
#1705
1"
#1710
0"
#1715
1"
#1720
b1010010100 #
b1010010100 -
0"
1$
#1725
b1 E
1"
#1730
0"
#1735
b11 E
1"
#1740
0"
#1745
1"
#1750
0"
#1755
1"
#1760
0"
0$
#1765
b10 E
1"
#1770
0"
#1775
b0 E
1"
#1780
0"
#1785
1"
#1790
0"
#1795
1"
#1800
b1010110010 #
b1010110010 -
0"
1$
#1805
b1 E
1"
#1810
0"
#1815
b11 E
1"
#1820
0"
#1825
1"
#1830
0"
#1835
1"
#1840
0"
0$
#1845
b10 E
1"
#1850
0"
#1855
b0 E
1"
#1860
0"
#1865
1"
#1870
0"
#1875
1"
#1880
b1011010000 #
b1011010000 -
0"
1$
#1885
b1 E
1"
#1890
0"
#1895
b11 E
1"
#1900
0"
#1905
1"
#1910
0"
#1915
1"
#1920
0"
0$
#1925
b10 E
1"
#1930
0"
#1935
b0 E
1"
#1940
0"
#1945
1"
#1950
0"
#1955
1"
#1960
b1011101110 #
b1011101110 -
0"
1$
#1965
b1 E
1"
#1970
0"
#1975
b11 E
1"
#1980
0"
#1985
1"
#1990
0"
#1995
1"
#2000
0"
0$
1'
#2005
b10 E
b1 G
1"
#2010
0"
#2015
b1 H
b0 E
b11 G
1"
#2020
0"
#2025
1"
#2030
0"
#2035
1"
#2040
b1100001100 #
b1100001100 -
0"
1$
#2045
b1 E
1"
#2050
0"
#2055
b10 H
b11 E
1"
#2060
0"
#2065
1"
#2070
0"
#2075
1"
#2080
0"
0$
#2085
b10 E
1"
#2090
0"
#2095
b0 E
1"
#2100
0"
#2105
1"
#2110
0"
#2115
1"
#2120
b1100101010 #
b1100101010 -
0"
1$
#2125
b1 E
1"
#2130
0"
#2135
b11 H
b10111110 A
b11 E
1"
#2140
0"
#2145
b100 H
b10111110 C
b1000101100101001 1
b0 2
b11011110 3
1"
#2150
0"
#2155
b101 H
b1000110000000111 D
1"
#2160
0"
0$
#2165
b110 H
b1111111110100001 ]
b110010101 \
b111111111111111 [
b10 E
1"
#2170
0"
#2175
b111 H
b1 :
b0 E
b1000000000000000 `
b1000000000000000 _
b1000000000000000 ^
b1000000000000000 e
b1000000010011010 d
1"
#2180
0"
#2185
b1000 H
b1000000000000000 c
b1000000000000000 b
b1000000000000000 a
b1000000000000000 d
1"
#2190
0"
#2195
b10 H
b1001001110001000 !
b1001001110001000 F
1"
#2200
b1101001000 #
b1101001000 -
0"
1$
#2205
b1 E
1"
#2210
0"
#2215
b11 H
b10111110 B
b10100000 A
b11 E
1"
#2220
0"
#2225
b100 H
b101011110 C
b111111111111111111111111111111111110101000000111 1
b1011 2
b10111011 3
1"
#2230
0"
#2235
b101 H
b111111111111111111111111111111111110101011001101 D
1"
#2240
0"
0$
#2245
b110 H
b1111 ]
b110100100 \
b1000000000000001 [
b10 E
1"
#2250
0"
#2255
b111 H
b10 :
b0 E
b11011010 d
1"
#2260
0"
#2265
b1000 H
b1000000000000000 d
1"
#2270
0"
#2275
b10 H
1"
#2280
b1101100110 #
b1101100110 -
0"
1$
#2285
b1 E
1"
#2290
0"
#2295
b11 H
b10100000 B
b10000010 A
b11 E
1"
#2300
0"
#2305
b100 H
b111100000 C
b10100 2
b10011000 3
1"
#2310
0"
#2315
b101 H
b111111111111111111111111111111111110101010110011 D
1"
#2320
0"
0$
#2325
b110 H
b110110011 \
b10 E
1"
#2330
0"
#2335
b111 H
b11 :
b0 E
b11100010 d
1"
#2340
0"
#2345
b1000 H
b1000000000000000 d
1"
#2350
0"
#2355
b10 H
1"
#2360
b1110000100 #
b1110000100 -
0"
1$
#2365
b1 E
1"
#2370
0"
#2375
b11 H
b10000010 B
b1100100 A
b11 E
1"
#2380
0"
#2385
b100 H
b1001000100 C
b11100 2
b1110101 3
1"
#2390
0"
#2395
b101 H
b111111111111111111111111111111111110101010011000 D
1"
#2400
0"
0$
#2405
b110 H
b111000010 \
b10 E
1"
#2410
0"
#2415
b111 H
b100 :
b0 E
b11101001 d
1"
#2420
0"
#2425
b1000 H
b1000000000000000 d
1"
#2430
0"
#2435
b10 H
1"
#2440
b1110100010 #
b1110100010 -
0"
1$
#2445
b1 E
1"
#2450
0"
#2455
b11 H
b1100100 B
b1000110 A
b11 E
1"
#2460
0"
#2465
b100 H
b1010001010 C
b100001 2
b1010010 3
1"
#2470
0"
#2475
b101 H
b111111111111111111111111111111111110101001111010 D
1"
#2480
0"
0$
#2485
b110 H
b111010001 \
b10 E
1"
#2490
0"
#2495
b111 H
b101 :
b0 E
b11110001 d
1"
#2500
0"
#2505
b1000 H
b1000000000000000 d
1"
#2510
0"
#2515
b10 H
1"
#2520
b1111000000 #
b1111000000 -
0"
1$
#2525
b1 E
1"
#2530
0"
#2535
b11 H
b1000110 B
b101000 A
b11 E
1"
#2540
0"
#2545
b100 H
b1010110010 C
b100110 2
b101110 3
1"
#2550
0"
#2555
b101 H
b111111111111111111111111111111111110101001011011 D
1"
#2560
0"
0$
#2565
b110 H
b111100000 \
b10 E
1"
#2570
0"
#2575
b111 H
b110 :
b0 E
b11111000 d
1"
#2580
0"
#2585
b1000 H
b1000000000000000 d
1"
#2590
0"
#2595
b10 H
1"
#2600
b1111011110 #
b1111011110 -
0"
1$
#2605
b1 E
1"
#2610
0"
#2615
b11 H
b101000 B
b1010 A
b11 E
1"
#2620
0"
#2625
b100 H
b1010111100 C
b101000 2
b1011 3
1"
#2630
0"
#2635
b101 H
b111111111111111111111111111111111110101000111010 D
1"
#2640
0"
0$
#2645
b110 H
b111101111 \
b10 E
1"
#2650
0"
#2655
b111 H
b111 :
b0 E
b100000000 d
1"
#2660
0"
#2665
b1000 H
b1000000000000000 d
1"
#2670
0"
#2675
b10 H
1"
#2680
b1111111100 #
b1111111100 -
0"
1$
#2685
b1 E
1"
#2690
0"
#2695
b11 H
b1010 B
b111111111111111111111111111111111111111111101100 A
b11 E
1"
#2700
0"
#2705
b100 H
b1010101000 C
b101001 2
b111111111111111111111111111111111111111111101000 3
1"
#2710
0"
#2715
b101 H
b111111111111111111111111111111111110101000011000 D
1"
#2720
0"
0$
#2725
b110 H
b111111110 \
b10 E
1"
#2730
0"
#2735
b111 H
b1000 :
b0 E
b100000111 d
1"
#2740
0"
#2745
b1000 H
b1000000000000000 d
1"
#2750
0"
#2755
b10 H
1"
#2760
b10000011010 #
b10000011010 -
0"
1$
#2765
b1 E
1"
#2770
0"
#2775
b11 H
b111111111111111111111111111111111111111111101100 B
b111111111111111111111111111111111111111111001110 A
b11 E
1"
#2780
0"
#2785
b100 H
b1001110110 C
b100111 2
b111111111111111111111111111111111111111111000101 3
1"
#2790
0"
#2795
b101 H
b111111111111111111111111111111111110100111110011 D
1"
#2800
0"
0$
#2805
b110 H
b1000001101 \
b10 E
1"
#2810
0"
#2815
b111 H
b1001 :
b0 E
b100001111 d
1"
#2820
0"
#2825
b1000 H
b1000000000000000 d
1"
#2830
0"
#2835
b10 H
1"
#2840
b10000111000 #
b10000111000 -
0"
1$
#2845
b1 E
1"
#2850
0"
#2855
b11 H
b111111111111111111111111111111111111111111001110 B
b111111111111111111111111111111111111111110110000 A
b11 E
1"
#2860
0"
#2865
b100 H
b1000100110 C
b100100 2
b111111111111111111111111111111111111111110100010 3
1"
#2870
0"
#2875
b101 H
b111111111111111111111111111111111110100111001101 D
1"
#2880
0"
0$
#2885
b110 H
b1000011100 \
b10 E
1"
#2890
0"
#2895
b111 H
b1010 :
b0 E
b100010110 d
1"
#2900
0"
#2905
b1000 H
b1000000000000000 d
1"
#2910
0"
#2915
b10 H
1"
#2920
b10001010110 #
b10001010110 -
0"
1$
#2925
b1 E
1"
#2930
0"
#2935
b11 H
b111111111111111111111111111111111111111110110000 B
b111111111111111111111111111111111111111110010010 A
b11 E
1"
#2940
0"
#2945
b100 H
b110111000 C
b100000 2
b111111111111111111111111111111111111111101111111 3
1"
#2950
0"
#2955
b101 H
b111111111111111111111111111111111110100110100110 D
1"
#2960
0"
0$
#2965
b110 H
b1000101011 \
b10 E
1"
#2970
0"
#2975
b111 H
b1011 :
b0 E
b100011110 d
1"
#2980
0"
#2985
b1000 H
b1000000000000000 d
1"
#2990
0"
#2995
b1 @
b0 ?
b1000000000000010 >
b1000000000000000 !
b1000000000000000 F
b1001 H
1"
#3000
b10001110100 #
b10001110100 -
0"
1$
#3005
b1010 H
b111111111111100 =
b111111111111100 <
b111111111111100 ;
b1 E
1"
#3010
0"
#3015
b0 H
b100000000000001 9
b1100000000000010 7
b1011111111111100 6
b1011111111111100 5
b1011111111111100 4
b10111111 X
b10111111 U
b10111111 R
b1000010 N
b1000010 M
b1000010 L
b11000001 K
b11000001 J
b11000001 I
b11 E
1"
#3020
0"
#3025
1"
#3030
0"
#3035
1"
#3040
0"
0$
#3045
b10 E
1"
#3050
0"
#3055
b0 E
1"
#3060
0"
#3065
1"
#3070
0"
#3075
1"
#3080
b10010010010 #
b10010010010 -
0"
1$
#3085
b1 E
1"
#3090
0"
#3095
b11 E
1"
#3100
0"
#3105
1"
#3110
0"
#3115
1"
#3120
0"
0$
#3125
b10 E
1"
#3130
0"
#3135
b0 E
1"
#3140
0"
#3145
1"
#3150
0"
#3155
1"
#3160
b10010110000 #
b10010110000 -
0"
1$
#3165
b1 E
1"
#3170
0"
#3175
b11 E
1"
#3180
0"
#3185
1"
#3190
0"
#3195
1"
#3200
0"
0$
#3205
b10 E
1"
#3210
0"
#3215
b0 E
1"
#3220
0"
#3225
1"
#3230
0"
#3235
1"
#3240
b10011001110 #
b10011001110 -
0"
1$
#3245
b1 E
1"
#3250
0"
#3255
b11 E
1"
#3260
0"
#3265
1"
#3270
0"
#3275
1"
#3280
0"
0$
#3285
b10 E
1"
#3290
0"
#3295
b0 E
1"
#3300
0"
#3305
1"
#3310
0"
#3315
1"
#3320
b10011101100 #
b10011101100 -
0"
1$
#3325
b1 E
1"
#3330
0"
#3335
b11 E
1"
#3340
0"
#3345
1"
#3350
0"
#3355
1"
#3360
0"
0$
#3365
b10 E
1"
#3370
0"
#3375
b0 E
1"
#3380
0"
#3385
1"
#3390
0"
#3395
1"
#3400
b10100001010 #
b10100001010 -
0"
1$
#3405
b1 E
1"
#3410
0"
#3415
b11 E
1"
#3420
0"
#3425
1"
#3430
0"
#3435
1"
#3440
0"
0$
#3445
b10 E
1"
#3450
0"
#3455
b0 E
1"
#3460
0"
#3465
1"
#3470
0"
#3475
1"
#3480
b10100101000 #
b10100101000 -
0"
1$
#3485
b1 E
1"
#3490
0"
#3495
b11 E
1"
#3500
0"
#3505
1"
#3510
0"
#3515
1"
#3520
0"
0$
