design/app/max10_galvano/source/pos_pid.v
module pos_pid
(
    input  wire        sys_rstn,
    input  wire        clk_pid,
    
    input  wire [15:0] kp,
    input  wire [15:0] ki,
    input  wire [15:0] kd,
    
    input  wire [15:0] dac_limit,
    input  wire [23:0] pid_i_saturation,
    input  wire [15:0] pos_target,
    input  wire [15:0] pos_adc,
    output reg  [15:0] pos_dac
);

reg signed [47:0] P, I, D, error, error_last, integrator;
reg signed [47:0] pid;
wire [15:0] limit0;
wire [15:0] limit1;

assign limit0 = 32768 - dac_limit;
assign limit1 = 32768 + dac_limit;

localparam STATE0 = 0;
localparam STATE1 = 1;
localparam STATE2 = 2;
reg [1:0] state;
always @(negedge sys_rstn or posedge clk_pid) begin
    if (!sys_rstn) begin
        state <= STATE0;
        error <= 0;
        error_last <= 0;
        integrator <= 0;
        P <= 0;
        I <= 0;
        D <= 0;
        pid <= 0;
        pos_dac <= 32768;
    end
    else if (clk_pid) begin
        error <= $signed({1'b0, pos_target}) - $signed({1'b0, pos_adc});
        error_last <= error;
        case(state)
            STATE0: begin // error has valid value
                state <= STATE1;
            end
            STATE1: begin // error_last has valid value
                state <= STATE2;
            end
            STATE2: begin
                P <= ($signed({1'b0, kp}) * error) >>> 10;
                I <= ($signed({1'b0, ki}) * integrator) >>> 10;
                D <= ($signed({1'b0, kd}) * (error - error_last)) >>> 10;
                pid <= (P + I + D);
            
                if ((-(integrator + error) < $signed({1'b0, pid_i_saturation})) && 
                    ( (integrator + error) < $signed({1'b0, pid_i_saturation})))
                    integrator <= integrator + error;
                
                if (pid > $signed({1'b0, dac_limit})) begin
                    pos_dac <= limit1;
                end
                else if (-pid > $signed({1'b0, dac_limit})) begin
                    pos_dac <= limit0;
                end
                else begin
                    pos_dac <= $unsigned($signed(32768) + pid);
                end
            end
        endcase
    end
end

endmodule

design/app/max10_galvano/source/pos_pid_tb.v
module tb();
    reg  clk, reset, spi_new_target_valid, pos_adc_data_valid;
    reg  [15:0] pos_adc, pos_target;
    wire [15:0] pos_dac;
    
    pos_pid pid
    (
       .sys_rstn(reset),
       .clk_pid(clk),
       
       .kp(16'd1200),
       .ki(16'd60),
       .kd(16'd1200),
       
       .dac_limit(16'd5000),
       .pid_i_saturation(24'd5000),
       .pos_target(pos_target),
       .pos_adc(pos_adc),
       .pos_dac(pos_dac)
    );

    always #5  clk = ~clk;
    always #10 pos_adc = pos_adc + 100;

    initial begin
        clk = 0;
        reset = 0;
        pos_adc = 0;
        pos_adc_data_valid = 0;
        spi_new_target_valid = 0;
        pos_target = 10000;
        
        $dumpfile("pid.vcd");
        $dumpvars;

        #100 reset = 1;
        #50000 $finish;
    end
endmodule

design/app/max10_galvano/source/pid.vcd
$date
	Mon Dec 21 23:27:08 2020
$end
$version
	Icarus Verilog
$end
$timescale
	1s
$end
$scope module tb $end
$var wire 16 ! pos_dac [15:0] $end
$var reg 1 " clk $end
$var reg 16 # pos_adc [15:0] $end
$var reg 1 $ pos_adc_data_valid $end
$var reg 16 % pos_target [15:0] $end
$var reg 1 & reset $end
$var reg 1 ' spi_new_target_valid $end
$scope module pid $end
$var wire 1 " clk_pid $end
$var wire 16 ( dac_limit [15:0] $end
$var wire 16 ) kd [15:0] $end
$var wire 16 * ki [15:0] $end
$var wire 16 + kp [15:0] $end
$var wire 24 , pid_i_saturation [23:0] $end
$var wire 16 - pos_adc [15:0] $end
$var wire 16 . pos_target [15:0] $end
$var wire 1 & sys_rstn $end
$var wire 16 / limit1 [15:0] $end
$var wire 16 0 limit0 [15:0] $end
$var reg 48 1 D [47:0] $end
$var reg 48 2 I [47:0] $end
$var reg 48 3 P [47:0] $end
$var reg 48 4 error [47:0] $end
$var reg 48 5 error_last [47:0] $end
$var reg 48 6 integrator [47:0] $end
$var reg 48 7 pid [47:0] $end
$var reg 16 8 pos_dac [15:0] $end
$var reg 2 9 state [1:0] $end
$upscope $end
$upscope $end
$enddefinitions $end
#0
$dumpvars
b0 9
b1000000000000000 8
b0 7
b0 6
b0 5
b0 4
b0 3
b0 2
b0 1
b110110001111000 0
b1001001110001000 /
b10011100010000 .
b0 -
b1001110001000 ,
b10010110000 +
b111100 *
b10010110000 )
b1001110001000 (
0'
0&
b10011100010000 %
0$
b0 #
0"
b1000000000000000 !
$end
#5
1"
#10
0"
b1100100 #
b1100100 -
#15
1"
#20
0"
b11001000 #
b11001000 -
#25
1"
#30
0"
b100101100 #
b100101100 -
#35
1"
#40
0"
b110010000 #
b110010000 -
#45
1"
#50
0"
b111110100 #
b111110100 -
#55
1"
#60
0"
b1001011000 #
b1001011000 -
#65
1"
#70
0"
b1010111100 #
b1010111100 -
#75
1"
#80
0"
b1100100000 #
b1100100000 -
#85
1"
#90
0"
b1110000100 #
b1110000100 -
#95
1"
#100
0"
b1111101000 #
b1111101000 -
1&
#105
b1 9
b10001100101000 4
1"
#110
0"
b10001001100 #
b10001001100 -
#115
b10 9
b10001100101000 5
b10001011000100 4
1"
#120
0"
b10010110000 #
b10010110000 -
#125
b111111111111111111111111111111111111111110001010 1
b10100010111101 3
b10001011000100 5
b10001001100000 4
1"
#130
0"
b10100010100 #
b10100010100 -
#135
b10100001000111 7
b10100001001000 3
b10001001100000 5
b10000111111100 4
1"
#140
0"
b10101111000 #
b10101111000 -
#145
b1001001110001000 !
b1001001110001000 8
b10011111010010 7
b10011111010011 3
b10000111111100 5
b10000110011000 4
1"
#150
0"
b10111011100 #
b10111011100 -
#155
b10011101011101 7
b10011101011110 3
b10000110011000 5
b10000100110100 4
1"
#160
0"
b11001000000 #
b11001000000 -
#165
b10011011101000 7
b10011011101000 3
b10000100110100 5
b10000011010000 4
1"
#170
0"
b11010100100 #
b11010100100 -
#175
b10011001110010 7
b10011001110011 3
b10000011010000 5
b10000001101100 4
1"
#180
0"
b11100001000 #
b11100001000 -
#185
b10010111111101 7
b10010111111110 3
b10000001101100 5
b10000000001000 4
1"
#190
0"
b11101101100 #
b11101101100 -
#195
b10010110001000 7
b10010110001001 3
b10000000001000 5
b1111110100100 4
1"
#200
0"
b11111010000 #
b11111010000 -
#205
b10010100010011 7
b10010100010100 3
b1111110100100 5
b1111101000000 4
1"
#210
0"
b100000110100 #
b100000110100 -
#215
b10010010011110 7
b10010010011111 3
b1111101000000 5
b1111011011100 4
1"
#220
0"
b100010011000 #
b100010011000 -
#225
b10010000101001 7
b10010000101001 3
b1111011011100 5
b1111001111000 4
1"
#230
0"
b100011111100 #
b100011111100 -
#235
b10001110110011 7
b10001110110100 3
b1111001111000 5
b1111000010100 4
1"
#240
0"
b100101100000 #
b100101100000 -
#245
b10001100111110 7
b10001100111111 3
b1111000010100 5
b1110110110000 4
1"
#250
0"
b100111000100 #
b100111000100 -
#255
b10001011001001 7
b10001011001010 3
b1110110110000 5
b1110101001100 4
1"
#260
0"
b101000101000 #
b101000101000 -
#265
b10001001010100 7
b10001001010101 3
b1110101001100 5
b1110011101000 4
1"
#270
0"
b101010001100 #
b101010001100 -
#275
b10000111011111 7
b10000111011111 3
b1110011101000 5
b1110010000100 4
1"
#280
0"
b101011110000 #
b101011110000 -
#285
b10000101101001 7
b10000101101010 3
b1110010000100 5
b1110000100000 4
1"
#290
0"
b101101010100 #
b101101010100 -
#295
b10000011110100 7
b10000011110101 3
b1110000100000 5
b1101110111100 4
1"
#300
0"
b101110111000 #
b101110111000 -
#305
b10000001111111 7
b10000010000000 3
b1101110111100 5
b1101101011000 4
1"
#310
0"
b110000011100 #
b110000011100 -
#315
b10000000001010 7
b10000000001011 3
b1101101011000 5
b1101011110100 4
1"
#320
0"
b110010000000 #
b110010000000 -
#325
b1111110010101 7
b1111110010101 3
b1101011110100 5
b1101010010000 4
1"
#330
0"
b110011100100 #
b110011100100 -
#335
b1111100011111 7
b1111100100000 3
b1101010010000 5
b1101000101100 4
1"
#340
0"
b110101001000 #
b110101001000 -
#345
b1111010101010 7
b1111010101011 3
b1101000101100 5
b1100111001000 4
1"
#350
0"
b110110101100 #
b110110101100 -
#355
b1111000110101 7
b1111000110110 3
b1100111001000 5
b1100101100100 4
1"
#360
0"
b111000010000 #
b111000010000 -
#365
b1110111000000 7
b1110111000001 3
b1100101100100 5
b1100100000000 4
1"
#370
0"
b111001110100 #
b111001110100 -
#375
b1110101001011 7
b1110101001100 3
b1100100000000 5
b1100010011100 4
1"
#380
0"
b111011011000 #
b111011011000 -
#385
b1110011010110 7
b1110011010110 3
b1100010011100 5
b1100000111000 4
1"
#390
0"
b111100111100 #
b111100111100 -
#395
b1110001100000 7
b1110001100001 3
b1100000111000 5
b1011111010100 4
1"
#400
0"
b111110100000 #
b111110100000 -
#405
b1101111101011 7
b1101111101100 3
b1011111010100 5
b1011101110000 4
1"
#410
0"
b1000000000100 #
b1000000000100 -
#415
b1101101110110 7
b1101101110111 3
b1011101110000 5
b1011100001100 4
1"
#420
0"
b1000001101000 #
b1000001101000 -
#425
b1101100000001 7
b1101100000010 3
b1011100001100 5
b1011010101000 4
1"
#430
0"
b1000011001100 #
b1000011001100 -
#435
b1101010001100 7
b1101010001100 3
b1011010101000 5
b1011001000100 4
1"
#440
0"
b1000100110000 #
b1000100110000 -
#445
b1101000010110 7
b1101000010111 3
b1011001000100 5
b1010111100000 4
1"
#450
0"
b1000110010100 #
b1000110010100 -
#455
b1100110100001 7
b1100110100010 3
b1010111100000 5
b1010101111100 4
1"
#460
0"
b1000111111000 #
b1000111111000 -
#465
b1100100101100 7
b1100100101101 3
b1010101111100 5
b1010100011000 4
1"
#470
0"
b1001001011100 #
b1001001011100 -
#475
b1100010110111 7
b1100010111000 3
b1010100011000 5
b1010010110100 4
1"
#480
0"
b1001011000000 #
b1001011000000 -
#485
b1100001000010 7
b1100001000010 3
b1010010110100 5
b1010001010000 4
1"
#490
0"
b1001100100100 #
b1001100100100 -
#495
b1011111001100 7
b1011111001101 3
b1010001010000 5
b1001111101100 4
1"
#500
0"
b1001110001000 #
b1001110001000 -
#505
b1011101010111 7
b1011101011000 3
b1001111101100 5
b1001110001000 4
1"
#510
0"
b1001111101100 #
b1001111101100 -
#515
b1011011100010 7
b1011011100011 3
b1001110001000 5
b1001100100100 4
1"
#520
0"
b1010001010000 #
b1010001010000 -
#525
b1001100100100 6
b1011001101101 7
b1011001101110 3
b1001100100100 5
b1001011000000 4
1"
#530
0"
b1010010110100 #
b1010010110100 -
#535
b1010111111000 7
b100011111 2
b1010111111001 3
b1001011000000 5
b1001001011100 4
1"
#540
0"
b1010100011000 #
b1010100011000 -
#545
b1011010100010 7
b1010110000011 3
b1001001011100 5
b1000111111000 4
1"
#550
0"
b1010101111100 #
b1010101111100 -
#555
b1011000101100 7
b1010100001110 3
b1000111111000 5
b1000110010100 4
1"
#560
0"
b1010111100000 #
b1010111100000 -
#565
b1010110110111 7
b1010010011001 3
b1000110010100 5
b1000100110000 4
1"
#570
0"
b1011001000100 #
b1011001000100 -
#575
b1010101000010 7
b1010000100100 3
b1000100110000 5
b1000011001100 4
1"
#580
0"
b1011010101000 #
b1011010101000 -
#585
b1010011001101 7
b1001110101111 3
b1000011001100 5
b1000001101000 4
1"
#590
0"
b1011100001100 #
b1011100001100 -
#595
b1010001011000 7
b1001100111001 3
b1000001101000 5
b1000000000100 4
1"
#600
0"
b1011101110000 #
b1011101110000 -
#605
b1001111100010 7
b1001011000100 3
b1000000000100 5
b111110100000 4
1"
#610
0"
b1011111010100 #
b1011111010100 -
#615
b1001101101101 7
b1001001001111 3
b111110100000 5
b111100111100 4
1"
#620
0"
b1100000111000 #
b1100000111000 -
#625
b1001001101101101 !
b1001001101101101 8
b1001011111000 7
b1000111011010 3
b111100111100 5
b111011011000 4
1"
#630
0"
b1100010011100 #
b1100010011100 -
#635
b1001001011111000 !
b1001001011111000 8
b1001010000011 7
b1000101100101 3
b111011011000 5
b111001110100 4
1"
#640
0"
b1100100000000 #
b1100100000000 -
#645
b1001001010000011 !
b1001001010000011 8
b1001000001110 7
b1000011101111 3
b111001110100 5
b111000010000 4
1"
#650
0"
b1100101100100 #
b1100101100100 -
#655
b1001001000001110 !
b1001001000001110 8
b1000110011000 7
b1000001111010 3
b111000010000 5
b110110101100 4
1"
#660
0"
b1100111001000 #
b1100111001000 -
#665
b1001000110011000 !
b1001000110011000 8
b1000100100011 7
b1000000000101 3
b110110101100 5
b110101001000 4
1"
#670
0"
b1101000101100 #
b1101000101100 -
#675
b1001000100100011 !
b1001000100100011 8
b1000010101110 7
b111110010000 3
b110101001000 5
b110011100100 4
1"
#680
0"
b1101010010000 #
b1101010010000 -
#685
b1001000010101110 !
b1001000010101110 8
b1000000111001 7
b111100011011 3
b110011100100 5
b110010000000 4
1"
#690
0"
b1101011110100 #
b1101011110100 -
#695
b1001000000111001 !
b1001000000111001 8
b111111000100 7
b111010100110 3
b110010000000 5
b110000011100 4
1"
#700
0"
b1101101011000 #
b1101101011000 -
#705
b1000111111000100 !
b1000111111000100 8
b111101001111 7
b111000110000 3
b110000011100 5
b101110111000 4
1"
#710
0"
b1101110111100 #
b1101110111100 -
#715
b1000111101001111 !
b1000111101001111 8
b111011011001 7
b110110111011 3
b101110111000 5
b101101010100 4
1"
#720
0"
b1110000100000 #
b1110000100000 -
#725
b1000111011011001 !
b1000111011011001 8
b111001100100 7
b110101000110 3
b101101010100 5
b101011110000 4
1"
#730
0"
b1110010000100 #
b1110010000100 -
#735
b1000111001100100 !
b1000111001100100 8
b110111101111 7
b110011010001 3
b101011110000 5
b101010001100 4
1"
#740
0"
b1110011101000 #
b1110011101000 -
#745
b1000110111101111 !
b1000110111101111 8
b110101111010 7
b110001011100 3
b101010001100 5
b101000101000 4
1"
#750
0"
b1110101001100 #
b1110101001100 -
#755
b1000110101111010 !
b1000110101111010 8
b110100000101 7
b101111100110 3
b101000101000 5
b100111000100 4
1"
#760
0"
b1110110110000 #
b1110110110000 -
#765
b1000110100000101 !
b1000110100000101 8
b110010001111 7
b101101110001 3
b100111000100 5
b100101100000 4
1"
#770
0"
b1111000010100 #
b1111000010100 -
#775
b1000110010001111 !
b1000110010001111 8
b110000011010 7
b101011111100 3
b100101100000 5
b100011111100 4
1"
#780
0"
b1111001111000 #
b1111001111000 -
#785
b1000110000011010 !
b1000110000011010 8
b101110100101 7
b101010000111 3
b100011111100 5
b100010011000 4
1"
#790
0"
b1111011011100 #
b1111011011100 -
#795
b1000101110100101 !
b1000101110100101 8
b101100110000 7
b101000010010 3
b100010011000 5
b100000110100 4
1"
#800
0"
b1111101000000 #
b1111101000000 -
#805
b1000101100110000 !
b1000101100110000 8
b101010111011 7
b100110011100 3
b100000110100 5
b11111010000 4
1"
#810
0"
b1111110100100 #
b1111110100100 -
#815
b1000101010111011 !
b1000101010111011 8
b101001000101 7
b100100100111 3
b11111010000 5
b11101101100 4
1"
#820
0"
b10000000001000 #
b10000000001000 -
#825
b1000101001000101 !
b1000101001000101 8
b100111010000 7
b100010110010 3
b11101101100 5
b11100001000 4
1"
#830
0"
b10000001101100 #
b10000001101100 -
#835
b1000100111010000 !
b1000100111010000 8
b100101011011 7
b100000111101 3
b11100001000 5
b11010100100 4
1"
#840
0"
b10000011010000 #
b10000011010000 -
#845
b1000100101011011 !
b1000100101011011 8
b100011100110 7
b11111001000 3
b11010100100 5
b11001000000 4
1"
#850
0"
b10000100110100 #
b10000100110100 -
#855
b1000100011100110 !
b1000100011100110 8
b100001110001 7
b11101010011 3
b11001000000 5
b10111011100 4
1"
#860
0"
b10000110011000 #
b10000110011000 -
#865
b1000100001110001 !
b1000100001110001 8
b11111111100 7
b11011011101 3
b10111011100 5
b10101111000 4
1"
#870
0"
b10000111111100 #
b10000111111100 -
#875
b1000011111111100 !
b1000011111111100 8
b11110000110 7
b11001101000 3
b10101111000 5
b10100010100 4
1"
#880
0"
b10001001100000 #
b10001001100000 -
#885
b1000011110000110 !
b1000011110000110 8
b11100010001 7
b10111110011 3
b10100010100 5
b10010110000 4
1"
#890
0"
b10001011000100 #
b10001011000100 -
#895
b1000011100010001 !
b1000011100010001 8
b11010011100 7
b10101111110 3
b10010110000 5
b10001001100 4
1"
#900
0"
b10001100101000 #
b10001100101000 -
#905
b1000011010011100 !
b1000011010011100 8
b11000100111 7
b10100001001 3
b10001001100 5
b1111101000 4
1"
#910
0"
b10001110001100 #
b10001110001100 -
#915
b1000011000100111 !
b1000011000100111 8
b10110110010 7
b10010010011 3
b1111101000 5
b1110000100 4
1"
#920
0"
b10001111110000 #
b10001111110000 -
#925
b1000010110110010 !
b1000010110110010 8
b10100111100 7
b10000011110 3
b1110000100 5
b1100100000 4
1"
#930
0"
b10010001010100 #
b10010001010100 -
#935
b1000010100111100 !
b1000010100111100 8
b10011000111 7
b1110101001 3
b1100100000 5
b1010111100 4
1"
#940
0"
b10010010111000 #
b10010010111000 -
#945
b1000010011000111 !
b1000010011000111 8
b10001010010 7
b1100110100 3
b1010111100 5
b1001011000 4
1"
#950
0"
b10010100011100 #
b10010100011100 -
#955
b1000010001010010 !
b1000010001010010 8
b1111011101 7
b1010111111 3
b1001011000 5
b111110100 4
1"
#960
0"
b10010110000000 #
b10010110000000 -
#965
b1000001111011101 !
b1000001111011101 8
b1101101000 7
b1001001001 3
b111110100 5
b110010000 4
1"
#970
0"
b10010111100100 #
b10010111100100 -
#975
b1000001101101000 !
b1000001101101000 8
b1011110010 7
b111010100 3
b110010000 5
b100101100 4
1"
#980
0"
b10011001001000 #
b10011001001000 -
#985
b1000001011110010 !
b1000001011110010 8
b1001111101 7
b101011111 3
b100101100 5
b11001000 4
1"
#990
0"
b10011010101100 #
b10011010101100 -
#995
b1000001001111101 !
b1000001001111101 8
b1000001000 7
b11101010 3
b11001000 5
b1100100 4
1"
#1000
0"
b10011100010000 #
b10011100010000 -
#1005
b1000001000001000 !
b1000001000001000 8
b110010011 7
b1110101 3
b1100100 5
b0 4
1"
#1010
0"
b10011101110100 #
b10011101110100 -
#1015
b1000000110010011 !
b1000000110010011 8
b100011110 7
b0 3
b0 5
b111111111111111111111111111111111111111110011100 4
1"
#1020
0"
b10011111011000 #
b10011111011000 -
#1025
b1000000100011110 !
b1000000100011110 8
b1001011000000 6
b10101001 7
b111111111111111111111111111111111111111110001010 3
b111111111111111111111111111111111111111110011100 5
b111111111111111111111111111111111111111100111000 4
1"
#1030
0"
b10100000111100 #
b10100000111100 -
#1035
b1000000010101001 !
b1000000010101001 8
b1000111111000 6
b110011 7
b100011001 2
b111111111111111111111111111111111111111100010101 3
b111111111111111111111111111111111111111100111000 5
b111111111111111111111111111111111111111011010100 4
1"
#1040
0"
b10100010100000 #
b10100010100000 -
#1045
b1000000000110011 !
b1000000000110011 8
b1000011001100 6
b111111111111111111111111111111111111111110111000 7
b100001101 2
b111111111111111111111111111111111111111010100000 3
b111111111111111111111111111111111111111011010100 5
b111111111111111111111111111111111111111001110000 4
1"
#1050
0"
b10100100000100 #
b10100100000100 -
#1055
b111111110111000 !
b111111110111000 8
b111100111100 6
b111111111111111111111111111111111111111100110111 7
b11111011 2
b111111111111111111111111111111111111111000101011 3
b111111111111111111111111111111111111111001110000 5
b111111111111111111111111111111111111111000001100 4
1"
#1060
0"
b10100101101000 #
b10100101101000 -
#1065
b111111100110111 !
b111111100110111 8
b110101001000 6
b111111111111111111111111111111111111111010110000 7
b11100100 2
b111111111111111111111111111111111111110110110110 3
b111111111111111111111111111111111111111000001100 5
b111111111111111111111111111111111111110110101000 4
1"
#1070
0"
b10100111001100 #
b10100111001100 -
#1075
b111111010110000 !
b111111010110000 8
b101011110000 6
b111111111111111111111111111111111111111000100100 7
b11000111 2
b111111111111111111111111111111111111110101000000 3
b111111111111111111111111111111111111110110101000 5
b111111111111111111111111111111111111110101000100 4
1"
#1080
0"
b10101000110000 #
b10101000110000 -
#1085
b111111000100100 !
b111111000100100 8
b100000110100 6
b111111111111111111111111111111111111110110010001 7
b10100100 2
b111111111111111111111111111111111111110011001011 3
b111111111111111111111111111111111111110101000100 5
b111111111111111111111111111111111111110011100000 4
1"
#1090
0"
b10101010010100 #
b10101010010100 -
#1095
b111110110010001 !
b111110110010001 8
b10100010100 6
b111111111111111111111111111111111111110011111001 7
b1111011 2
b111111111111111111111111111111111111110001010110 3
b111111111111111111111111111111111111110011100000 5
b111111111111111111111111111111111111110001111100 4
1"
#1100
0"
b10101011111000 #
b10101011111000 -
#1105
b111110011111001 !
b111110011111001 8
b110010000 6
b111111111111111111111111111111111111110001011011 7
b1001100 2
b111111111111111111111111111111111111101111100001 3
b111111111111111111111111111111111111110001111100 5
b111111111111111111111111111111111111110000011000 4
1"
#1110
0"
b10101101011100 #
b10101101011100 -
#1115
b111110001011011 !
b111110001011011 8
b111111111111111111111111111111111111110110101000 6
b111111111111111111111111111111111111101110110111 7
b10111 2
b111111111111111111111111111111111111101101101100 3
b111111111111111111111111111111111111110000011000 5
b111111111111111111111111111111111111101110110100 4
1"
#1120
0"
b10101111000000 #
b10101111000000 -
#1125
b111101110110111 !
b111101110110111 8
b111111111111111111111111111111111111100101011100 6
b111111111111111111111111111111111111101100001101 7
b111111111111111111111111111111111111111111011100 2
b111111111111111111111111111111111111101011110110 3
b111111111111111111111111111111111111101110110100 5
b111111111111111111111111111111111111101101010000 4
1"
#1130
0"
b10110000100100 #
b10110000100100 -
#1135
b111101100001101 !
b111101100001101 8
b111111111111111111111111111111111111010010101100 6
b111111111111111111111111111111111111101001011100 7
b111111111111111111111111111111111111111110011100 2
b111111111111111111111111111111111111101010000001 3
b111111111111111111111111111111111111101101010000 5
b111111111111111111111111111111111111101011101100 4
1"
#1140
0"
b10110010001000 #
b10110010001000 -
#1145
b111101001011100 !
b111101001011100 8
b111111111111111111111111111111111110111110011000 6
b111111111111111111111111111111111111100110100111 7
b111111111111111111111111111111111111111101010110 2
b111111111111111111111111111111111111101000001100 3
b111111111111111111111111111111111111101011101100 5
b111111111111111111111111111111111111101010001000 4
1"
#1150
0"
b10110011101100 #
b10110011101100 -
#1155
b111100110100111 !
b111100110100111 8
b111111111111111111111111111111111111100011101100 7
b111111111111111111111111111111111111111100001001 2
b111111111111111111111111111111111111100110010111 3
b111111111111111111111111111111111111101010001000 5
b111111111111111111111111111111111111101000100100 4
1"
#1160
0"
b10110101010000 #
b10110101010000 -
#1165
b111100011101100 !
b111100011101100 8
b111111111111111111111111111111111111100000101010 7
b111111111111111111111111111111111111100100100010 3
b111111111111111111111111111111111111101000100100 5
b111111111111111111111111111111111111100111000000 4
1"
#1170
0"
b10110110110100 #
b10110110110100 -
#1175
b111100000101010 !
b111100000101010 8
b111111111111111111111111111111111111011110110101 7
b111111111111111111111111111111111111100010101101 3
b111111111111111111111111111111111111100111000000 5
b111111111111111111111111111111111111100101011100 4
1"
#1180
0"
b10111000011000 #
b10111000011000 -
#1185
b111011110110101 !
b111011110110101 8
b111111111111111111111111111111111111011101000000 7
b111111111111111111111111111111111111100000110111 3
b111111111111111111111111111111111111100101011100 5
b111111111111111111111111111111111111100011111000 4
1"
#1190
0"
b10111001111100 #
b10111001111100 -
#1195
b111011101000000 !
b111011101000000 8
b111111111111111111111111111111111111011011001010 7
b111111111111111111111111111111111111011111000010 3
b111111111111111111111111111111111111100011111000 5
b111111111111111111111111111111111111100010010100 4
1"
#1200
0"
b10111011100000 #
b10111011100000 -
#1205
b111011011001010 !
b111011011001010 8
b111111111111111111111111111111111111011001010101 7
b111111111111111111111111111111111111011101001101 3
b111111111111111111111111111111111111100010010100 5
b111111111111111111111111111111111111100000110000 4
1"
#1210
0"
b10111101000100 #
b10111101000100 -
#1215
b111011001010101 !
b111011001010101 8
b111111111111111111111111111111111111010111100000 7
b111111111111111111111111111111111111011011011000 3
b111111111111111111111111111111111111100000110000 5
b111111111111111111111111111111111111011111001100 4
1"
#1220
0"
b10111110101000 #
b10111110101000 -
#1225
b111010111100000 !
b111010111100000 8
b111111111111111111111111111111111111010101101011 7
b111111111111111111111111111111111111011001100011 3
b111111111111111111111111111111111111011111001100 5
b111111111111111111111111111111111111011101101000 4
1"
#1230
0"
b11000000001100 #
b11000000001100 -
#1235
b111010101101011 !
b111010101101011 8
b111111111111111111111111111111111111010011110110 7
b111111111111111111111111111111111111010111101101 3
b111111111111111111111111111111111111011101101000 5
b111111111111111111111111111111111111011100000100 4
1"
#1240
0"
b11000001110000 #
b11000001110000 -
#1245
b111010011110110 !
b111010011110110 8
b111111111111111111111111111111111111010010000000 7
b111111111111111111111111111111111111010101111000 3
b111111111111111111111111111111111111011100000100 5
b111111111111111111111111111111111111011010100000 4
1"
#1250
0"
b11000011010100 #
b11000011010100 -
#1255
b111010010000000 !
b111010010000000 8
b111111111111111111111111111111111111010000001011 7
b111111111111111111111111111111111111010100000011 3
b111111111111111111111111111111111111011010100000 5
b111111111111111111111111111111111111011000111100 4
1"
#1260
0"
b11000100111000 #
b11000100111000 -
#1265
b111010000001011 !
b111010000001011 8
b111111111111111111111111111111111111001110010110 7
b111111111111111111111111111111111111010010001110 3
b111111111111111111111111111111111111011000111100 5
b111111111111111111111111111111111111010111011000 4
1"
#1270
0"
b11000110011100 #
b11000110011100 -
#1275
b111001110010110 !
b111001110010110 8
b111111111111111111111111111111111111001100100001 7
b111111111111111111111111111111111111010000011001 3
b111111111111111111111111111111111111010111011000 5
b111111111111111111111111111111111111010101110100 4
1"
#1280
0"
b11001000000000 #
b11001000000000 -
#1285
b111001100100001 !
b111001100100001 8
b111111111111111111111111111111111111001010101100 7
b111111111111111111111111111111111111001110100011 3
b111111111111111111111111111111111111010101110100 5
b111111111111111111111111111111111111010100010000 4
1"
#1290
0"
b11001001100100 #
b11001001100100 -
#1295
b111001010101100 !
b111001010101100 8
b111111111111111111111111111111111111001000110110 7
b111111111111111111111111111111111111001100101110 3
b111111111111111111111111111111111111010100010000 5
b111111111111111111111111111111111111010010101100 4
1"
#1300
0"
b11001011001000 #
b11001011001000 -
#1305
b111001000110110 !
b111001000110110 8
b111111111111111111111111111111111111000111000001 7
b111111111111111111111111111111111111001010111001 3
b111111111111111111111111111111111111010010101100 5
b111111111111111111111111111111111111010001001000 4
1"
#1310
0"
b11001100101100 #
b11001100101100 -
#1315
b111000111000001 !
b111000111000001 8
b111111111111111111111111111111111111000101001100 7
b111111111111111111111111111111111111001001000100 3
b111111111111111111111111111111111111010001001000 5
b111111111111111111111111111111111111001111100100 4
1"
#1320
0"
b11001110010000 #
b11001110010000 -
#1325
b111000101001100 !
b111000101001100 8
b111111111111111111111111111111111111000011010111 7
b111111111111111111111111111111111111000111001111 3
b111111111111111111111111111111111111001111100100 5
b111111111111111111111111111111111111001110000000 4
1"
#1330
0"
b11001111110100 #
b11001111110100 -
#1335
b111000011010111 !
b111000011010111 8
b111111111111111111111111111111111111000001100010 7
b111111111111111111111111111111111111000101011010 3
b111111111111111111111111111111111111001110000000 5
b111111111111111111111111111111111111001100011100 4
1"
#1340
0"
b11010001011000 #
b11010001011000 -
#1345
b111000001100010 !
b111000001100010 8
b111111111111111111111111111111111110111111101101 7
b111111111111111111111111111111111111000011100100 3
b111111111111111111111111111111111111001100011100 5
b111111111111111111111111111111111111001010111000 4
1"
#1350
0"
b11010010111100 #
b11010010111100 -
#1355
b110111111101101 !
b110111111101101 8
b111111111111111111111111111111111110111101110111 7
b111111111111111111111111111111111111000001101111 3
b111111111111111111111111111111111111001010111000 5
b111111111111111111111111111111111111001001010100 4
1"
#1360
0"
b11010100100000 #
b11010100100000 -
#1365
b110111101110111 !
b110111101110111 8
b111111111111111111111111111111111110111100000010 7
b111111111111111111111111111111111110111111111010 3
b111111111111111111111111111111111111001001010100 5
b111111111111111111111111111111111111000111110000 4
1"
#1370
0"
b11010110000100 #
b11010110000100 -
#1375
b110111100000010 !
b110111100000010 8
b111111111111111111111111111111111110111010001101 7
b111111111111111111111111111111111110111110000101 3
b111111111111111111111111111111111111000111110000 5
b111111111111111111111111111111111111000110001100 4
1"
#1380
0"
b11010111101000 #
b11010111101000 -
#1385
b110111010001101 !
b110111010001101 8
b111111111111111111111111111111111110111000011000 7
b111111111111111111111111111111111110111100010000 3
b111111111111111111111111111111111111000110001100 5
b111111111111111111111111111111111111000100101000 4
1"
#1390
0"
b11011001001100 #
b11011001001100 -
#1395
b110111000011000 !
b110111000011000 8
b111111111111111111111111111111111110110110100011 7
b111111111111111111111111111111111110111010011010 3
b111111111111111111111111111111111111000100101000 5
b111111111111111111111111111111111111000011000100 4
1"
#1400
0"
b11011010110000 #
b11011010110000 -
#1405
b110110110100011 !
b110110110100011 8
b111111111111111111111111111111111110110100101101 7
b111111111111111111111111111111111110111000100101 3
b111111111111111111111111111111111111000011000100 5
b111111111111111111111111111111111111000001100000 4
1"
#1410
0"
b11011100010100 #
b11011100010100 -
#1415
b110110100101101 !
b110110100101101 8
b111111111111111111111111111111111110110010111000 7
b111111111111111111111111111111111110110110110000 3
b111111111111111111111111111111111111000001100000 5
b111111111111111111111111111111111110111111111100 4
1"
#1420
0"
b11011101111000 #
b11011101111000 -
#1425
b110110010111000 !
b110110010111000 8
b111111111111111111111111111111111110110001000011 7
b111111111111111111111111111111111110110100111011 3
b111111111111111111111111111111111110111111111100 5
b111111111111111111111111111111111110111110011000 4
1"
#1430
0"
b11011111011100 #
b11011111011100 -
#1435
b110110001111000 !
b110110001111000 8
b111111111111111111111111111111111110101111001110 7
b111111111111111111111111111111111110110011000110 3
b111111111111111111111111111111111110111110011000 5
b111111111111111111111111111111111110111100110100 4
1"
#1440
0"
b11100001000000 #
b11100001000000 -
#1445
b111111111111111111111111111111111110101101011001 7
b111111111111111111111111111111111110110001010000 3
b111111111111111111111111111111111110111100110100 5
b111111111111111111111111111111111110111011010000 4
1"
#1450
0"
b11100010100100 #
b11100010100100 -
